acex/core/automation_engine/__init__.py
acex/core/automation_engine/automationengine.py
acex/core/compilers/__init__.py
acex/core/compilers/compiled_logical_node.py
acex/core/compilers/config_compiler.py
acex/core/config_map/__init__.py
acex/core/config_map/config_map.py
acex/core/config_map/context.py
acex/core/config_map/filter.py
acex/core/configuration/__init__.py
acex/core/configuration/components/__init__.py
acex/core/configuration/components/base_component.py
acex/core/configuration/components/interfaces/__init__.py
acex/core/configuration/components/interfaces/interfaces.py
acex/core/configuration/components/system/__init__.py
acex/core/configuration/components/system/system.py
acex/core/configuration/configuration.py
acex/core/database/__init__.py
acex/core/database/connection.py
acex/core/database/db_manager.py
acex/core/datastore/__init__.py
acex/core/datastore/attribute_map.py
acex/core/datastore/datastore.py
acex/core/exceptions/__init__.py
acex/core/exceptions/standard.py
acex/core/inventory/__init__.py
acex/core/inventory/inventory.py
acex/core/inventory/logical_node_service.py
acex/core/inventory/node_service.py
acex/core/models/__init__.py
acex/core/models/asset.py
acex/core/models/attribute_value.py
acex/core/models/device_config.py
acex/core/models/external_value.py
acex/core/models/interfaces.py
acex/core/models/logical_node.py
acex/core/models/management_connections.py
acex/core/models/node.py
acex/core/models/single_attribute.py
acex/core/service/__init__.py
acex/core/service/service_base.py
acex_core-0.2.4.dist-info/METADATA
acex_core-0.2.4.dist-info/WHEEL
acex_core-0.2.4.dist-info/RECORD
