Metadata-Version: 2.4
Name: acex-core
Version: 0.2.4
Summary: Core components for acex framework
Author: Johan Lahti
Author-email: johan.lahti@acebit.se
Requires-Python: >=3.13
Classifier: Programming Language :: Python :: 3
Classifier: Programming Language :: Python :: 3.13
Classifier: Programming Language :: Python :: 3.14
Requires-Dist: psycopg2-binary (>=2.9.10)
Requires-Dist: requests (>=2.32.4)
Requires-Dist: sqlmodel (>=0.0.24)
